{
    "embed": [
        {
            "label": "HTML",
            "path": "16.2/JA/grid/json-binding/fiddle/demo.html"
        },
        {
            "label": "JS",
            "path": "16.2/JA/grid/json-binding/fiddle/demo.js"
        },
        {
            "label": "CSS",
            "path": "fiddle/demo.css"
        },
        {
            "type": "htmlpage",
            "label": "Result",
            "url": "https://damyanpetev.github.io/samples-test/16.2/JA/grid/json-binding/index.html"
        }
    ]
}